velmu/__init__.py
velmu/_version.py
velmu/abc.py
velmu/api.py
velmu/client.py
velmu/config.py
velmu/embed.py
velmu/errors.py
velmu/flags.py
velmu/gateway.py
velmu/permissions.py
velmu/state.py
velmu/utils.py
velmu/ext/__init__.py
velmu/ext/commands/__init__.py
velmu/ext/commands/checks.py
velmu/ext/commands/converters.py
velmu/ext/commands/core.py
velmu/ext/tasks/__init__.py
velmu/models/__init__.py
velmu/models/activity.py
velmu/models/attachment.py
velmu/models/base.py
velmu/models/channel.py
velmu/models/components.py
velmu/models/embed.py
velmu/models/file.py
velmu/models/guild.py
velmu/models/interaction.py
velmu/models/invite.py
velmu/models/user.py
velmu-1.0.6.dist-info/licenses/LICENSE
velmu-1.0.6.dist-info/METADATA
velmu-1.0.6.dist-info/WHEEL
velmu-1.0.6.dist-info/top_level.txt
velmu-1.0.6.dist-info/RECORD
