Metadata-Version: 2.4
Name: velmu
Version: 1.0.6
Summary: A Python wrapper for the Velmu API
Author-email: Velmu Team <dev@velmu.com>
License: MIT License
Project-URL: Homepage, https://velmu.com
Project-URL: Bug Tracker, https://github.com/velmu/issues
Keywords: velmu,api,wrapper,bot,sdk
Classifier: Development Status :: 4 - Beta
Classifier: Intended Audience :: Developers
Classifier: License :: OSI Approved :: MIT License
Classifier: Programming Language :: Python :: 3
Classifier: Programming Language :: Python :: 3.8
Classifier: Programming Language :: Python :: 3.9
Classifier: Programming Language :: Python :: 3.10
Classifier: Topic :: Software Development :: Libraries :: Python Modules
Classifier: Topic :: Internet :: WWW/HTTP
Requires-Python: >=3.8
License-File: LICENSE
Requires-Dist: aiohttp>=3.8.0
Requires-Dist: python-socketio>=5.0.0
Requires-Dist: websockets>=10.0
Dynamic: license-file
